AUTHORS.txt
LICENSE.txt
MANIFEST.in
README.md
gpyopt.py
requirements.txt
setup.cfg
setup.py
GPyOpt/__init__.py
GPyOpt/__version__.py
GPyOpt.egg-info/PKG-INFO
GPyOpt.egg-info/SOURCES.txt
GPyOpt.egg-info/dependency_links.txt
GPyOpt.egg-info/requires.txt
GPyOpt.egg-info/top_level.txt
GPyOpt/acquisitions/EI.py
GPyOpt/acquisitions/EI_mcmc.py
GPyOpt/acquisitions/LCB.py
GPyOpt/acquisitions/LCB_mcmc.py
GPyOpt/acquisitions/LP.py
GPyOpt/acquisitions/MPI.py
GPyOpt/acquisitions/MPI_mcmc.py
GPyOpt/acquisitions/__init__.py
GPyOpt/acquisitions/base.py
GPyOpt/core/__init__.py
GPyOpt/core/bo.py
GPyOpt/core/errors.py
GPyOpt/core/evaluators/__init__.py
GPyOpt/core/evaluators/base.py
GPyOpt/core/evaluators/batch_local_penalization.py
GPyOpt/core/evaluators/batch_random.py
GPyOpt/core/evaluators/batch_thompson.py
GPyOpt/core/evaluators/sequential.py
GPyOpt/core/task/__init__.py
GPyOpt/core/task/cost.py
GPyOpt/core/task/objective.py
GPyOpt/core/task/space.py
GPyOpt/core/task/variables.py
GPyOpt/experiment_design/__init__.py
GPyOpt/experiment_design/base.py
GPyOpt/experiment_design/grid_design.py
GPyOpt/experiment_design/latin_design.py
GPyOpt/experiment_design/random_design.py
GPyOpt/experiment_design/sobol_design.py
GPyOpt/interface/__init__.py
GPyOpt/interface/config_parser.py
GPyOpt/interface/driver.py
GPyOpt/interface/func_loader.py
GPyOpt/interface/output.py
GPyOpt/methods/__init__.py
GPyOpt/methods/bayesian_optimization.py
GPyOpt/methods/modular_bayesian_optimization.py
GPyOpt/models/__init__.py
GPyOpt/models/base.py
GPyOpt/models/gpmodel.py
GPyOpt/models/input_warped_gpmodel.py
GPyOpt/models/rfmodel.py
GPyOpt/models/warpedgpmodel.py
GPyOpt/objective_examples/__init__.py
GPyOpt/objective_examples/experiments1d.py
GPyOpt/objective_examples/experiments2d.py
GPyOpt/objective_examples/experimentsNd.py
GPyOpt/optimization/__init__.py
GPyOpt/optimization/acquisition_optimizer.py
GPyOpt/optimization/anchor_points_generator.py
GPyOpt/optimization/optimizer.py
GPyOpt/plotting/__init__.py
GPyOpt/plotting/plots_bo.py
GPyOpt/util/__init__.py
GPyOpt/util/arguments_manager.py
GPyOpt/util/duplicate_manager.py
GPyOpt/util/general.py
