Metadata-Version: 1.1
Name: GPyOpt
Version: 1.2.1
Summary: The Bayesian Optimization Toolbox
Home-page: http://sheffieldml.github.io/GPyOpt/
Author: -Aki Vehtari
Author-email: j.h.gonzalez@sheffield.ac.uk
License: BSD 3-clause
Keywords: machine-learning gaussian-processes kernels optimization
Platform: UNKNOWN
Classifier: License :: OSI Approved :: BSD License
Classifier: Natural Language :: English
Classifier: Operating System :: MacOS :: MacOS X
Classifier: Operating System :: Microsoft :: Windows
Classifier: Operating System :: POSIX :: Linux
Classifier: Programming Language :: Python :: 2.7
Classifier: Topic :: Scientific/Engineering :: Artificial Intelligence
